sberbank/__init__.py
sberbank/admin.py
sberbank/apps.py
sberbank/exceptions.py
sberbank/models.py
sberbank/service.py
sberbank/setup.py
sberbank/tasks.py
sberbank/urls.py
sberbank/views.py
sberbank/migrations/0001_initial.py
sberbank/migrations/0002_auto_20180307_0652.py
sberbank/migrations/0003_banklog_checksum.py
sberbank/migrations/0004_auto_20180510_0741.py
sberbank/migrations/__init__.py
sberbank-0.38.dist-info/DESCRIPTION.rst
sberbank-0.38.dist-info/METADATA
sberbank-0.38.dist-info/RECORD
sberbank-0.38.dist-info/WHEEL
sberbank-0.38.dist-info/metadata.json
sberbank-0.38.dist-info/top_level.txt
